{
  "ticker": "DASTY",
  "fetchedAt": "2026-06-08T09:07:47.625870Z",
  "people": [
    {
      "qid": "Q115735422",
      "name": "Pascal Daloz",
      "role_at_company": "Chief Executive Officer",
      "source_field": "executives",
      "career": {
        "qid": "Q115735422",
        "name": "Pascal Daloz",
        "dateOfBirth": null,
        "birthPlace": null,
        "image": null,
        "occupations": [],
        "education": [],
        "employers": [],
        "positions": [
          {
            "title": "president",
            "company": null,
            "start": "2026-02-01",
            "end": null
          },
          {
            "title": "chief executive officer",
            "company": null,
            "start": "2024-01-01",
            "end": null
          }
        ]
      }
    }
  ]
}