{"ticker":"FSLY","updated":"2026-06-15T02:48:37Z","source":"yahoo","currency":"USD","income":[{"calendarYear":"2025","date":"2025-12-31","revenue":624018000.0,"costOfRevenue":267815000.0,"grossProfit":356203000.0,"operatingExpenses":474788000.0,"operatingIncome":-118585000.0,"ebitda":-28638000.0,"netIncome":-121677000.0,"epsdiluted":-0.83,"eps":-0.83},{"calendarYear":"2024","date":"2024-12-31","revenue":543676000.0,"costOfRevenue":247738000.0,"grossProfit":295938000.0,"operatingExpenses":449989000.0,"operatingIncome":-154051000.0,"ebitda":-79071000.0,"netIncome":-158058000.0,"epsdiluted":-1.14,"eps":-1.14},{"calendarYear":"2023","date":"2023-12-31","revenue":505988000.0,"costOfRevenue":239660000.0,"grossProfit":266328000.0,"operatingExpenses":460040000.0,"operatingIncome":-193712000.0,"ebitda":-57232000.0,"netIncome":-133088000.0,"epsdiluted":-1.03,"eps":-1.03},{"calendarYear":"2022","date":"2022-12-31","revenue":432725000.0,"costOfRevenue":222944000.0,"grossProfit":209781000.0,"operatingExpenses":455980000.0,"operatingIncome":-246199000.0,"ebitda":-120478000.0,"netIncome":-190774000.0,"epsdiluted":-1.57,"eps":-1.57},{"calendarYear":"2021","date":"2021-12-31","revenue":null,"costOfRevenue":null,"grossProfit":null,"operatingExpenses":null,"operatingIncome":null,"ebitda":null,"netIncome":null,"epsdiluted":null,"eps":null}],"balance":[{"calendarYear":"2025","date":"2025-12-31","cashAndCashEquivalents":180563000.0,"shortTermInvestments":181196000.0,"totalCurrentAssets":506709000.0,"totalAssets":1499477000.0,"totalDebt":430187000.0,"totalLiabilities":569899000.0,"totalStockholdersEquity":929578000.0,"netDebt":181276000.0},{"calendarYear":"2024","date":"2024-12-31","cashAndCashEquivalents":286175000.0,"shortTermInvestments":9707000.0,"totalCurrentAssets":440195000.0,"totalAssets":1451359000.0,"totalDebt":404658000.0,"totalLiabilities":486109000.0,"totalStockholdersEquity":965250000.0,"netDebt":51439000.0},{"calendarYear":"2023","date":"2023-12-31","cashAndCashEquivalents":107921000.0,"shortTermInvestments":214799000.0,"totalCurrentAssets":463673000.0,"totalAssets":1525191000.0,"totalDebt":433319000.0,"totalLiabilities":545703000.0,"totalStockholdersEquity":979488000.0,"netDebt":235586000.0},{"calendarYear":"2022","date":"2022-12-31","cashAndCashEquivalents":143391000.0,"shortTermInvestments":374581000.0,"totalCurrentAssets":636483000.0,"totalAssets":1896113000.0,"totalDebt":833538000.0,"totalLiabilities":940955000.0,"totalStockholdersEquity":955158000.0,"netDebt":561319000.0},{"calendarYear":"2021","date":"2021-12-31","cashAndCashEquivalents":null,"shortTermInvestments":null,"totalCurrentAssets":null,"totalAssets":null,"totalDebt":null,"totalLiabilities":null,"totalStockholdersEquity":null,"netDebt":null}],"cashflow":[{"calendarYear":"2025","date":"2025-12-31","operatingCashFlow":94444000.0,"capitalExpenditure":-46351000.0,"freeCashFlow":48093000.0,"stockBasedCompensation":117323000.0,"dividendsPaid":null},{"calendarYear":"2024","date":"2024-12-31","operatingCashFlow":16406000.0,"capitalExpenditure":-37214000.0,"freeCashFlow":-20808000.0,"stockBasedCompensation":107930000.0,"dividendsPaid":null},{"calendarYear":"2023","date":"2023-12-31","operatingCashFlow":362000.0,"capitalExpenditure":-32268000.0,"freeCashFlow":-31906000.0,"stockBasedCompensation":136303000.0,"dividendsPaid":null},{"calendarYear":"2022","date":"2022-12-31","operatingCashFlow":-69632000.0,"capitalExpenditure":-80318000.0,"freeCashFlow":-149950000.0,"stockBasedCompensation":145796000.0,"dividendsPaid":null},{"calendarYear":"2021","date":"2021-12-31","operatingCashFlow":null,"capitalExpenditure":null,"freeCashFlow":null,"stockBasedCompensation":null,"dividendsPaid":null}]}