{"ticker":"ILMN","updated":"2026-06-15T02:50:14Z","source":"yahoo","currency":"USD","income":[{"calendarYear":"2025","date":"2025-12-31","revenue":4343000000.0,"costOfRevenue":1473000000.0,"grossProfit":2870000000.0,"operatingExpenses":2053000000.0,"operatingIncome":817000000.0,"ebitda":1457000000.0,"netIncome":850000000.0,"epsdiluted":5.45,"eps":5.45},{"calendarYear":"2024","date":"2024-12-31","revenue":4372000000.0,"costOfRevenue":1511000000.0,"grossProfit":2861000000.0,"operatingExpenses":2261000000.0,"operatingIncome":600000000.0,"ebitda":-725000000.0,"netIncome":-1223000000.0,"epsdiluted":-7.69,"eps":-7.69},{"calendarYear":"2023","date":"2023-12-31","revenue":4504000000.0,"costOfRevenue":1760000000.0,"grossProfit":2744000000.0,"operatingExpenses":2966000000.0,"operatingIncome":-222000000.0,"ebitda":-608000000.0,"netIncome":-1161000000.0,"epsdiluted":-7.34,"eps":-7.34},{"calendarYear":"2022","date":"2022-12-31","revenue":4584000000.0,"costOfRevenue":1612000000.0,"grossProfit":2972000000.0,"operatingExpenses":2618000000.0,"operatingIncome":354000000.0,"ebitda":-3916000000.0,"netIncome":-4404000000.0,"epsdiluted":-28.0,"eps":-28.0},{"calendarYear":"2021","date":"2021-12-31","revenue":null,"costOfRevenue":null,"grossProfit":null,"operatingExpenses":null,"operatingIncome":null,"ebitda":null,"netIncome":null,"epsdiluted":null,"eps":null}],"balance":[{"calendarYear":"2025","date":"2025-12-31","cashAndCashEquivalents":1418000000.0,"shortTermInvestments":215000000.0,"totalCurrentAssets":3289000000.0,"totalAssets":6644000000.0,"totalDebt":2553000000.0,"totalLiabilities":3921000000.0,"totalStockholdersEquity":2723000000.0,"netDebt":571000000.0},{"calendarYear":"2024","date":"2024-12-31","cashAndCashEquivalents":1127000000.0,"shortTermInvestments":93000000.0,"totalCurrentAssets":2746000000.0,"totalAssets":6303000000.0,"totalDebt":2622000000.0,"totalLiabilities":3930000000.0,"totalStockholdersEquity":2373000000.0,"netDebt":862000000.0},{"calendarYear":"2023","date":"2023-12-31","cashAndCashEquivalents":1048000000.0,"shortTermInvestments":6000000.0,"totalCurrentAssets":2609000000.0,"totalAssets":10111000000.0,"totalDebt":2262000000.0,"totalLiabilities":4366000000.0,"totalStockholdersEquity":5745000000.0,"netDebt":441000000.0},{"calendarYear":"2022","date":"2022-12-31","cashAndCashEquivalents":2011000000.0,"shortTermInvestments":26000000.0,"totalCurrentAssets":3561000000.0,"totalAssets":12252000000.0,"totalDebt":3555000000.0,"totalLiabilities":5653000000.0,"totalStockholdersEquity":6599000000.0,"netDebt":724000000.0},{"calendarYear":"2021","date":"2021-12-31","cashAndCashEquivalents":null,"shortTermInvestments":null,"totalCurrentAssets":null,"totalAssets":null,"totalDebt":null,"totalLiabilities":null,"totalStockholdersEquity":null,"netDebt":null}],"cashflow":[{"calendarYear":"2025","date":"2025-12-31","operatingCashFlow":1079000000.0,"capitalExpenditure":-148000000.0,"freeCashFlow":931000000.0,"stockBasedCompensation":275000000.0,"dividendsPaid":null},{"calendarYear":"2024","date":"2024-12-31","operatingCashFlow":837000000.0,"capitalExpenditure":-128000000.0,"freeCashFlow":709000000.0,"stockBasedCompensation":370000000.0,"dividendsPaid":null},{"calendarYear":"2023","date":"2023-12-31","operatingCashFlow":478000000.0,"capitalExpenditure":-195000000.0,"freeCashFlow":283000000.0,"stockBasedCompensation":380000000.0,"dividendsPaid":null},{"calendarYear":"2022","date":"2022-12-31","operatingCashFlow":392000000.0,"capitalExpenditure":-286000000.0,"freeCashFlow":106000000.0,"stockBasedCompensation":366000000.0,"dividendsPaid":null},{"calendarYear":"2021","date":"2021-12-31","operatingCashFlow":null,"capitalExpenditure":null,"freeCashFlow":null,"stockBasedCompensation":null,"dividendsPaid":null}]}