{"ticker":"PDD","updated":"2026-06-15T02:49:35Z","source":"yahoo","currency":"USD","income":[{"calendarYear":"2025","date":"2025-12-31","revenue":431845713000.0,"costOfRevenue":188801753000.0,"grossProfit":243043960000.0,"operatingExpenses":149941829000.0,"operatingIncome":93102131000.0,"ebitda":122446654000.0,"netIncome":97842539000.0,"epsdiluted":67.04,"eps":67.04},{"calendarYear":"2024","date":"2024-12-31","revenue":393836097000.0,"costOfRevenue":153900374000.0,"grossProfit":239935723000.0,"operatingExpenses":131512861000.0,"operatingIncome":108422862000.0,"ebitda":135324955000.0,"netIncome":112434512000.0,"epsdiluted":76.0,"eps":76.0},{"calendarYear":"2023","date":"2023-12-31","revenue":247639205000.0,"costOfRevenue":91723577000.0,"grossProfit":155915628000.0,"operatingExpenses":97216866000.0,"operatingIncome":58698762000.0,"ebitda":73813347000.0,"netIncome":60026544000.0,"epsdiluted":41.16,"eps":41.16},{"calendarYear":"2022","date":"2022-12-31","revenue":130557589000.0,"costOfRevenue":31462298000.0,"grossProfit":99095291000.0,"operatingExpenses":68693370000.0,"operatingIncome":30401921000.0,"ebitda":39205753000.0,"netIncome":31538062000.0,"epsdiluted":21.92,"eps":21.92}],"balance":[{"calendarYear":"2025","date":"2025-12-31","cashAndCashEquivalents":108900587000.0,"shortTermInvestments":313407682000.0,"totalCurrentAssets":518979892000.0,"totalAssets":630044327000.0,"totalDebt":5378795000.0,"totalLiabilities":216659171000.0,"totalStockholdersEquity":413385156000.0,"netDebt":null},{"calendarYear":"2024","date":"2024-12-31","cashAndCashEquivalents":57768053000.0,"shortTermInvestments":273791856000.0,"totalCurrentAssets":415648232000.0,"totalAssets":505034316000.0,"totalDebt":10607140000.0,"totalLiabilities":191721192000.0,"totalStockholdersEquity":313313124000.0,"netDebt":null},{"calendarYear":"2023","date":"2023-12-31","cashAndCashEquivalents":59794469000.0,"shortTermInvestments":157415365000.0,"totalCurrentAssets":294750472000.0,"totalAssets":348078120000.0,"totalDebt":10165901000.0,"totalLiabilities":160836513000.0,"totalStockholdersEquity":187241607000.0,"netDebt":null},{"calendarYear":"2022","date":"2022-12-31","cashAndCashEquivalents":34326192000.0,"shortTermInvestments":115112554000.0,"totalCurrentAssets":216617876000.0,"totalAssets":237119953000.0,"totalDebt":16934324000.0,"totalLiabilities":119349042000.0,"totalStockholdersEquity":117770911000.0,"netDebt":null},{"calendarYear":"2021","date":"2021-12-31","cashAndCashEquivalents":null,"shortTermInvestments":null,"totalCurrentAssets":null,"totalAssets":null,"totalDebt":null,"totalLiabilities":null,"totalStockholdersEquity":null,"netDebt":5362192000.0}],"cashflow":[{"calendarYear":"2025","date":"2025-12-31","operatingCashFlow":106938690000.0,"capitalExpenditure":-1145077000.0,"freeCashFlow":105793613000.0,"stockBasedCompensation":7936971000.0,"dividendsPaid":null},{"calendarYear":"2024","date":"2024-12-31","operatingCashFlow":121929292000.0,"capitalExpenditure":-967137000.0,"freeCashFlow":120962155000.0,"stockBasedCompensation":9883564000.0,"dividendsPaid":null},{"calendarYear":"2023","date":"2023-12-31","operatingCashFlow":94162531000.0,"capitalExpenditure":-583879000.0,"freeCashFlow":93578652000.0,"stockBasedCompensation":7078794000.0,"dividendsPaid":null},{"calendarYear":"2022","date":"2022-12-31","operatingCashFlow":48507860000.0,"capitalExpenditure":-635716000.0,"freeCashFlow":47872144000.0,"stockBasedCompensation":7718365000.0,"dividendsPaid":null},{"calendarYear":"2021","date":"2021-12-31","operatingCashFlow":null,"capitalExpenditure":null,"freeCashFlow":null,"stockBasedCompensation":null,"dividendsPaid":null}]}