{
  "qid": "Q5300803",
  "name": "Doug Parker",
  "dateOfBirth": "1962-01-01",
  "birthPlace": null,
  "image": "http://commons.wikimedia.org/wiki/Special:FilePath/DougParker.jpg",
  "occupations": [
    "entrepreneur",
    "chief executive officer"
  ],
  "education": [
    "Albion College",
    "Vanderbilt University"
  ],
  "employers": [
    {
      "company": "American Airlines Group",
      "start": null,
      "end": null
    }
  ],
  "positions": [
    {
      "title": "chief executive officer",
      "company": null,
      "start": null,
      "end": null
    }
  ],
  "currentTickers": [
    "U"
  ]
}