{
  "generatedAt": "2026-06-19T05:44:18.059219Z",
  "totalAttempted": 38,
  "etfs": {
    "AGG": {
      "ok": false,
      "msg": "all 3 strategies failed (S1: etf_scraper: ValueError: Was expecting an 'as of date' indicator, instead found: set() | S2: direct CSV parser returned 0 holdings | S3: yahoo HTTP 429)",
      "fetchedAt": "2026-06-19T05:44:20.410500Z"
    },
    "BND": {
      "ok": false,
      "msg": "all 3 strategies failed (S1: etf_scraper: ConnectionError: HTTPSConnectionPool(host='eds.ecs.gisp.c1.vanguard.com', port=443): Max retries exceeded with url: /eds-eip-distributions-service/holdings/holding-details-history/0928.json?as-of-date=2026-05-31 (Caused by NameResolutionError(\"HTTPSConnection(host='eds.ecs.gisp.c1.vanguard.com', port=443): Failed to resolve 'eds.ecs.gisp.c1.vanguard.com' ([Errno -2] Name or service not known)\")) | S2: no direct-fetch URL registered for ticker | S3: yahoo HTTP 429)",
      "fetchedAt": "2026-06-19T05:44:21.000840Z"
    },
    "DIA": {
      "ok": false,
      "msg": "all 3 strategies failed (S1: etf_scraper: TypeError: Expected file path name or file-like object, got <class 'bytes'> type | S2: no direct-fetch URL registered for ticker | S3: yahoo HTTP 429)",
      "fetchedAt": "2026-06-19T05:44:21.790691Z"
    },
    "EEM": {
      "ok": false,
      "msg": "all 3 strategies failed (S1: etf_scraper: ValueError: Was expecting an 'as of date' indicator, instead found: set() | S2: direct CSV parser returned 0 holdings | S3: yahoo HTTP 429)",
      "fetchedAt": "2026-06-19T05:44:23.588965Z"
    },
    "EFA": {
      "ok": false,
      "msg": "all 3 strategies failed (S1: etf_scraper: ValueError: Was expecting an 'as of date' indicator, instead found: set() | S2: direct CSV parser returned 0 holdings | S3: yahoo HTTP 429)",
      "fetchedAt": "2026-06-19T05:44:24.987447Z"
    },
    "HYG": {
      "ok": false,
      "msg": "all 3 strategies failed (S1: etf_scraper: ValueError: Was expecting an 'as of date' indicator, instead found: set() | S2: direct CSV parser returned 0 holdings | S3: yahoo HTTP 429)",
      "fetchedAt": "2026-06-19T05:44:26.566510Z"
    },
    "IJH": {
      "ok": false,
      "msg": "all 3 strategies failed (S1: etf_scraper: ValueError: Was expecting an 'as of date' indicator, instead found: set() | S2: direct CSV parser returned 0 holdings | S3: yahoo HTTP 429)",
      "fetchedAt": "2026-06-19T05:44:28.037525Z"
    },
    "IJR": {
      "ok": false,
      "msg": "all 3 strategies failed (S1: etf_scraper: ValueError: Was expecting an 'as of date' indicator, instead found: set() | S2: direct CSV parser returned 0 holdings | S3: yahoo HTTP 429)",
      "fetchedAt": "2026-06-19T05:44:29.582839Z"
    },
    "IVV": {
      "ok": false,
      "msg": "all 3 strategies failed (S1: etf_scraper: ValueError: Was expecting an 'as of date' indicator, instead found: set() | S2: direct CSV parser returned 0 holdings | S3: yahoo HTTP 429)",
      "fetchedAt": "2026-06-19T05:44:30.901794Z"
    },
    "IWD": {
      "ok": false,
      "msg": "all 3 strategies failed (S1: etf_scraper: ValueError: Was expecting an 'as of date' indicator, instead found: set() | S2: direct CSV parser returned 0 holdings | S3: yahoo HTTP 429)",
      "fetchedAt": "2026-06-19T05:44:32.066961Z"
    },
    "IWF": {
      "ok": false,
      "msg": "all 3 strategies failed (S1: etf_scraper: ValueError: Was expecting an 'as of date' indicator, instead found: set() | S2: direct CSV parser returned 0 holdings | S3: yahoo HTTP 429)",
      "fetchedAt": "2026-06-19T05:44:33.452941Z"
    },
    "IWM": {
      "ok": false,
      "msg": "all 3 strategies failed (S1: etf_scraper: ValueError: Was expecting an 'as of date' indicator, instead found: set() | S2: direct CSV parser returned 0 holdings | S3: yahoo HTTP 429)",
      "fetchedAt": "2026-06-19T05:44:35.044942Z"
    },
    "IYR": {
      "ok": false,
      "msg": "all 3 strategies failed (S1: etf_scraper: ValueError: Was expecting an 'as of date' indicator, instead found: set() | S2: direct CSV parser returned 0 holdings | S3: yahoo HTTP 429)",
      "fetchedAt": "2026-06-19T05:44:36.412019Z"
    },
    "IYT": {
      "ok": false,
      "msg": "all 3 strategies failed (S1: etf_scraper: ValueError: Was expecting an 'as of date' indicator, instead found: set() | S2: direct CSV parser returned 0 holdings | S3: yahoo HTTP 429)",
      "fetchedAt": "2026-06-19T05:44:37.687131Z"
    },
    "QQQ": {
      "ok": false,
      "msg": "all 3 strategies failed (S1: etf_scraper: ParserError: Error tokenizing data. C error: Expected 1 fields in line 11, saw 13\n | S2: no direct-fetch URL registered for ticker | S3: yahoo HTTP 429)",
      "fetchedAt": "2026-06-19T05:44:38.978633Z"
    },
    "QQQM": {
      "ok": false,
      "msg": "all 3 strategies failed (S1: etf_scraper: ParserError: Error tokenizing data. C error: Expected 1 fields in line 11, saw 13\n | S2: no direct-fetch URL registered for ticker | S3: yahoo HTTP 429)",
      "fetchedAt": "2026-06-19T05:44:40.436326Z"
    },
    "RSP": {
      "ok": false,
      "msg": "all 3 strategies failed (S1: etf_scraper: ParserError: Error tokenizing data. C error: Expected 1 fields in line 11, saw 13\n | S2: no direct-fetch URL registered for ticker | S3: yahoo HTTP 429)",
      "fetchedAt": "2026-06-19T05:44:40.986134Z"
    },
    "SPY": {
      "ok": false,
      "msg": "all 3 strategies failed (S1: etf_scraper: TypeError: Expected file path name or file-like object, got <class 'bytes'> type | S2: no direct-fetch URL registered for ticker | S3: yahoo HTTP 429)",
      "fetchedAt": "2026-06-19T05:44:41.613108Z"
    },
    "TIP": {
      "ok": false,
      "msg": "all 3 strategies failed (S1: etf_scraper: ValueError: Was expecting an 'as of date' indicator, instead found: set() | S2: direct CSV parser returned 0 holdings | S3: yahoo HTTP 429)",
      "fetchedAt": "2026-06-19T05:44:43.413254Z"
    },
    "VEA": {
      "ok": false,
      "msg": "all 3 strategies failed (S1: etf_scraper: ConnectionError: HTTPSConnectionPool(host='eds.ecs.gisp.c1.vanguard.com', port=443): Max retries exceeded with url: /eds-eip-distributions-service/holdings/holding-details-history/0936.json?as-of-date=2026-05-31 (Caused by NameResolutionError(\"HTTPSConnection(host='eds.ecs.gisp.c1.vanguard.com', port=443): Failed to resolve 'eds.ecs.gisp.c1.vanguard.com' ([Errno -2] Name or service not known)\")) | S2: no direct-fetch URL registered for ticker | S3: yahoo HTTP 429)",
      "fetchedAt": "2026-06-19T05:44:43.971333Z"
    },
    "VNQ": {
      "ok": false,
      "msg": "all 3 strategies failed (S1: etf_scraper: ConnectionError: HTTPSConnectionPool(host='eds.ecs.gisp.c1.vanguard.com', port=443): Max retries exceeded with url: /eds-eip-distributions-service/holdings/holding-details-history/0986.json?as-of-date=2026-05-31 (Caused by NameResolutionError(\"HTTPSConnection(host='eds.ecs.gisp.c1.vanguard.com', port=443): Failed to resolve 'eds.ecs.gisp.c1.vanguard.com' ([Errno -2] Name or service not known)\")) | S2: no direct-fetch URL registered for ticker | S3: yahoo HTTP 429)",
      "fetchedAt": "2026-06-19T05:44:44.461166Z"
    },
    "VOO": {
      "ok": false,
      "msg": "all 3 strategies failed (S1: etf_scraper: ConnectionError: HTTPSConnectionPool(host='eds.ecs.gisp.c1.vanguard.com', port=443): Max retries exceeded with url: /eds-eip-distributions-service/holdings/holding-details-history/0968.json?as-of-date=2026-05-31 (Caused by NameResolutionError(\"HTTPSConnection(host='eds.ecs.gisp.c1.vanguard.com', port=443): Failed to resolve 'eds.ecs.gisp.c1.vanguard.com' ([Errno -2] Name or service not known)\")) | S2: no direct-fetch URL registered for ticker | S3: yahoo HTTP 429)",
      "fetchedAt": "2026-06-19T05:44:44.986523Z"
    },
    "VTI": {
      "ok": false,
      "msg": "all 3 strategies failed (S1: etf_scraper: ConnectionError: HTTPSConnectionPool(host='eds.ecs.gisp.c1.vanguard.com', port=443): Max retries exceeded with url: /eds-eip-distributions-service/holdings/holding-details-history/0970.json?as-of-date=2026-05-31 (Caused by NameResolutionError(\"HTTPSConnection(host='eds.ecs.gisp.c1.vanguard.com', port=443): Failed to resolve 'eds.ecs.gisp.c1.vanguard.com' ([Errno -2] Name or service not known)\")) | S2: no direct-fetch URL registered for ticker | S3: yahoo HTTP 429)",
      "fetchedAt": "2026-06-19T05:44:45.527941Z"
    },
    "VTV": {
      "ok": false,
      "msg": "all 3 strategies failed (S1: etf_scraper: ConnectionError: HTTPSConnectionPool(host='eds.ecs.gisp.c1.vanguard.com', port=443): Max retries exceeded with url: /eds-eip-distributions-service/holdings/holding-details-history/0966.json?as-of-date=2026-05-31 (Caused by NameResolutionError(\"HTTPSConnection(host='eds.ecs.gisp.c1.vanguard.com', port=443): Failed to resolve 'eds.ecs.gisp.c1.vanguard.com' ([Errno -2] Name or service not known)\")) | S2: no direct-fetch URL registered for ticker | S3: yahoo HTTP 429)",
      "fetchedAt": "2026-06-19T05:44:46.010873Z"
    },
    "VUG": {
      "ok": false,
      "msg": "all 3 strategies failed (S1: etf_scraper: ConnectionError: HTTPSConnectionPool(host='eds.ecs.gisp.c1.vanguard.com', port=443): Max retries exceeded with url: /eds-eip-distributions-service/holdings/holding-details-history/0967.json?as-of-date=2026-05-31 (Caused by NameResolutionError(\"HTTPSConnection(host='eds.ecs.gisp.c1.vanguard.com', port=443): Failed to resolve 'eds.ecs.gisp.c1.vanguard.com' ([Errno -2] Name or service not known)\")) | S2: no direct-fetch URL registered for ticker | S3: yahoo HTTP 429)",
      "fetchedAt": "2026-06-19T05:44:46.554401Z"
    },
    "VWO": {
      "ok": false,
      "msg": "all 3 strategies failed (S1: etf_scraper: ConnectionError: HTTPSConnectionPool(host='eds.ecs.gisp.c1.vanguard.com', port=443): Max retries exceeded with url: /eds-eip-distributions-service/holdings/holding-details-history/0964.json?as-of-date=2026-05-31 (Caused by NameResolutionError(\"HTTPSConnection(host='eds.ecs.gisp.c1.vanguard.com', port=443): Failed to resolve 'eds.ecs.gisp.c1.vanguard.com' ([Errno -2] Name or service not known)\")) | S2: no direct-fetch URL registered for ticker | S3: yahoo HTTP 429)",
      "fetchedAt": "2026-06-19T05:44:47.012688Z"
    },
    "VYM": {
      "ok": false,
      "msg": "all 3 strategies failed (S1: etf_scraper: ConnectionError: HTTPSConnectionPool(host='eds.ecs.gisp.c1.vanguard.com', port=443): Max retries exceeded with url: /eds-eip-distributions-service/holdings/holding-details-history/0923.json?as-of-date=2026-05-31 (Caused by NameResolutionError(\"HTTPSConnection(host='eds.ecs.gisp.c1.vanguard.com', port=443): Failed to resolve 'eds.ecs.gisp.c1.vanguard.com' ([Errno -2] Name or service not known)\")) | S2: no direct-fetch URL registered for ticker | S3: yahoo HTTP 429)",
      "fetchedAt": "2026-06-19T05:44:47.468725Z"
    },
    "XLB": {
      "ok": false,
      "msg": "all 3 strategies failed (S1: etf_scraper: TypeError: Expected file path name or file-like object, got <class 'bytes'> type | S2: no direct-fetch URL registered for ticker | S3: yahoo HTTP 429)",
      "fetchedAt": "2026-06-19T05:44:48.424216Z"
    },
    "XLC": {
      "ok": false,
      "msg": "all 3 strategies failed (S1: etf_scraper: TypeError: Expected file path name or file-like object, got <class 'bytes'> type | S2: no direct-fetch URL registered for ticker | S3: yahoo HTTP 429)",
      "fetchedAt": "2026-06-19T05:44:49.010146Z"
    },
    "XLE": {
      "ok": false,
      "msg": "all 3 strategies failed (S1: etf_scraper: TypeError: Expected file path name or file-like object, got <class 'bytes'> type | S2: no direct-fetch URL registered for ticker | S3: yahoo HTTP 429)",
      "fetchedAt": "2026-06-19T05:44:49.595452Z"
    },
    "XLF": {
      "ok": false,
      "msg": "all 3 strategies failed (S1: etf_scraper: TypeError: Expected file path name or file-like object, got <class 'bytes'> type | S2: no direct-fetch URL registered for ticker | S3: yahoo HTTP 429)",
      "fetchedAt": "2026-06-19T05:44:50.187063Z"
    },
    "XLI": {
      "ok": false,
      "msg": "all 3 strategies failed (S1: etf_scraper: TypeError: Expected file path name or file-like object, got <class 'bytes'> type | S2: no direct-fetch URL registered for ticker | S3: yahoo HTTP 429)",
      "fetchedAt": "2026-06-19T05:44:50.787025Z"
    },
    "XLK": {
      "ok": false,
      "msg": "all 3 strategies failed (S1: etf_scraper: TypeError: Expected file path name or file-like object, got <class 'bytes'> type | S2: no direct-fetch URL registered for ticker | S3: yahoo HTTP 429)",
      "fetchedAt": "2026-06-19T05:44:51.377990Z"
    },
    "XLP": {
      "ok": false,
      "msg": "all 3 strategies failed (S1: etf_scraper: TypeError: Expected file path name or file-like object, got <class 'bytes'> type | S2: no direct-fetch URL registered for ticker | S3: yahoo HTTP 429)",
      "fetchedAt": "2026-06-19T05:44:51.966307Z"
    },
    "XLRE": {
      "ok": false,
      "msg": "all 3 strategies failed (S1: etf_scraper: TypeError: Expected file path name or file-like object, got <class 'bytes'> type | S2: no direct-fetch URL registered for ticker | S3: yahoo HTTP 429)",
      "fetchedAt": "2026-06-19T05:44:52.655044Z"
    },
    "XLU": {
      "ok": false,
      "msg": "all 3 strategies failed (S1: etf_scraper: TypeError: Expected file path name or file-like object, got <class 'bytes'> type | S2: no direct-fetch URL registered for ticker | S3: yahoo HTTP 429)",
      "fetchedAt": "2026-06-19T05:44:53.264295Z"
    },
    "XLV": {
      "ok": false,
      "msg": "all 3 strategies failed (S1: etf_scraper: TypeError: Expected file path name or file-like object, got <class 'bytes'> type | S2: no direct-fetch URL registered for ticker | S3: yahoo HTTP 429)",
      "fetchedAt": "2026-06-19T05:44:53.861778Z"
    },
    "XLY": {
      "ok": false,
      "msg": "all 3 strategies failed (S1: etf_scraper: TypeError: Expected file path name or file-like object, got <class 'bytes'> type | S2: no direct-fetch URL registered for ticker | S3: yahoo HTTP 429)",
      "fetchedAt": "2026-06-19T05:44:54.446494Z"
    }
  },
  "totalSucceeded": 0,
  "sourcesUsed": {}
}